{
  "version": "3.0",
  "lastUpdated": "2026-04-04T09:55:31.341Z",
  "activeFeatures": {},
  "primaryFeature": null,
  "archivedFeatures": {},
  "pipeline": {
    "currentPhase": 1,
    "level": "Starter",
    "phaseHistory": []
  },
  "session": {
    "startedAt": "2026-04-04T09:50:12.767Z",
    "onboardingCompleted": false,
    "lastActivity": "2026-04-04T09:53:25.030Z"
  },
  "history": [
    {
      "timestamp": "2026-04-04T09:53:24.535Z",
      "action": "session_end",
      "feature": null,
      "details": "Session ended"
    },
    {
      "timestamp": "2026-04-04T09:53:25.031Z",
      "action": "session_end",
      "feature": null,
      "details": "Session ended"
    }
  ],
  "_snapshotTimestamp": "2026-04-04T09:57:29.335Z",
  "_reason": "pre-compress",
  "_jitPartial": false
}